<?xml version="1.0" encoding="UTF-8"?>
<!DOCTYPE struts PUBLIC "-//Apache Software Foundation//DTD Struts Configuration 2.0//EN"
        "http://struts.apache.org/dtds/struts-2.0.dtd">
<struts>
	<package name="shelfManager" extends="struts-default">
		<action name="shelfManage" class="shelfManageAction" method="shelfManage">
		</action>
		
		<action name="deleteJointApp" class="shelfManageAction" method="deleteJointApp"></action>
		
		<action name="change_notify_url" class="shelfManageAction" method="change_notify_url"></action>
		<action name="change_md5_key" class="shelfManageAction" method="change_md5_key"></action>
	</package>
</struts>